{
  "nodes": [
    {
      "id": "Root Module Base",
      "guid": -9796,
      "type": "Xnoise.RootModuleBase, Assembly-CSharp, Version=1.0.0.0, Culture=neutral, PublicKeyToken=null",
      "position": {
        "x": 280.0,
        "y": -120.0,
        "normalized": {
          "x": 0.919145048,
          "y": -0.3939193,
          "magnitude": 1.0,
          "sqrMagnitude": 1.0
        },
        "magnitude": 304.63092,
        "sqrMagnitude": 92800.0
      },
      "inputs": {}
    },
    {
      "id": "Billow",
      "guid": -9962,
      "type": "Xnoise.BillowNode, Assembly-CSharp, Version=1.0.0.0, Culture=neutral, PublicKeyToken=null",
      "position": {
        "x": -8.0,
        "y": -136.0,
        "normalized": {
          "x": -0.0587220229,
          "y": -0.9982744,
          "magnitude": 1.0,
          "sqrMagnitude": 1.0
        },
        "magnitude": 136.235092,
        "sqrMagnitude": 18560.0
      },
      "inputs": {
        "frequency": 1.0,
        "lacunarity": 3.0,
        "persistence": 2.0,
        "Octaves": 42,
        "Seed": -1,
        "Quality": 2
      }
    },
    {
      "id": "Renderer",
      "guid": -17718,
      "type": "Xnoise.Renderer, Assembly-CSharp, Version=1.0.0.0, Culture=neutral, PublicKeyToken=null",
      "position": {
        "x": 280.0,
        "y": -24.0,
        "normalized": {
          "x": 0.9963466,
          "y": -0.08540114,
          "normalized": {
            "x": 0.996346653,
            "y": -0.08540115,
            "magnitude": 1.0,
            "sqrMagnitude": 1.0
          },
          "magnitude": 0.99999994,
          "sqrMagnitude": 0.9999999
        },
        "magnitude": 281.0267,
        "sqrMagnitude": 78976.0
      },
      "inputs": {}
    }
  ],
  "connections": [
    {
      "fromNodeGuid": -9962,
      "toNodeGuid": -9796,
      "inputField": "Input"
    },
    {
      "fromNodeGuid": -9962,
      "toNodeGuid": -17718,
      "inputField": "Input"
    }
  ],
  "blackboardPosition": {
    "x": 632.0,
    "y": -1064.0,
    "normalized": {
      "x": 0.5106881,
      "y": -0.859766066,
      "magnitude": 1.0,
      "sqrMagnitude": 1.0
    },
    "magnitude": 1237.5459,
    "sqrMagnitude": 1531520.0
  }
}